{
  "version": "https://jsonfeed.org/version/1.1",
  "title": "📋 Daily Review — Article Training Feedback",
  "home_page_url": "https://zirnhelt.github.io/super-rss-feed",
  "feed_url": "https://zirnhelt.github.io/super-rss-feed/feed-review.json",
  "description": "20 articles for daily training feedback",
  "authors": [
    {
      "name": "Erich's AI Curator"
    }
  ],
  "language": "en",
  "_generated_at": "2026-07-23T06:40:02.562922+00:00",
  "_today": "wednesday",
  "_today_label": "Repair Culture & Practical Tech",
  "items": [
    {
      "id": "https://wltribune.com/2026/07/22/electricity-demand-breaks-record-amid-heat-wave-bc-hydro-says/",
      "url": "https://wltribune.com/2026/07/22/electricity-demand-breaks-record-amid-heat-wave-bc-hydro-says/",
      "title": "Electricity demand breaks record amid heat wave, BC Hydro says",
      "content_html": "## Electricity demand breaks record amid heat wave, BC Hydro says Published 5:22 pm Wednesday, July 22, 2026 In many parts of Canada, air conditioners can help keep homes comfortable during the hottest days of the summer. (Wikimedia Commons) ((Wikimedia Commons)) BC Hydro says customers set a new all-time summer peak electricity demand on Tuesday. Between 5 and 6 p.m. – the hour customers use the most electricity – usage reached 8,715 megawatts, surpassing the previous summer record of 8,652 megawatts set in August 2025. BC Hydro says another record could be broken Wednesday amid the ongoing",
      "date_published": "2026-07-23T00:22:43+00:00",
      "authors": [
        {
          "name": "Williams Lake Tribune",
          "url": "https://wltribune.com"
        }
      ],
      "_score": 90,
      "_quality": 85,
      "_relevance": 88,
      "_local_score": 100,
      "_category": "local",
      "_content_type": "breaking",
      "_selection_bucket": "high",
      "_theme_scores": {
        "monday": 44,
        "tuesday": 28,
        "wednesday": 39,
        "thursday": 35,
        "friday": 65,
        "saturday": 25,
        "sunday": 73
      },
      "_today": "wednesday",
      "_today_label": "Repair Culture & Practical Tech",
      "image": "https://wltribune.com/wp-content/uploads/sites/6/2026/07/260723-BPD-QUIZ-Air-conditioners.jpg?w=1024"
    },
    {
      "id": "https://100milefreepress.net/2026/07/22/village-of-clinton-placed-on-evacuation-alert-bonaparte-plateau-evacuation-order-expanded/",
      "url": "https://100milefreepress.net/2026/07/22/village-of-clinton-placed-on-evacuation-alert-bonaparte-plateau-evacuation-order-expanded/",
      "title": "Village of Clinton placed on evacuation alert, Bonaparte Plateau evacuation order expanded",
      "content_html": "## Village of Clinton placed on evacuation alert, Bonaparte Plateau evacuation order expanded Published 5:30 pm Wednesday, July 22, 2026 **By Patrick Davies** 1/3 An evacuation order and alert map from the Thompson-Nicola Regional District due to the Fiftynine Creek Wildfire. (TNRD) The Thompson-Nicola Regional District (TNRD) and the Village of Clinton have issued evacuation alerts for the area between the Pear Lake Wildfire and Fiftynine Creek Wildfire, and the TNRD has expanded an evacuation order for the latter blaze. On Wednesday, July 22, the TNRD and Clinton issued evacuation alerts",
      "date_published": "2026-07-23T00:30:00+00:00",
      "authors": [
        {
          "name": "100 Mile Free Press",
          "url": "https://www.100milefreepress.net"
        }
      ],
      "_score": 85,
      "_quality": 80,
      "_relevance": 88,
      "_local_score": 85,
      "_category": "local",
      "_content_type": "breaking",
      "_selection_bucket": "high",
      "_theme_scores": {
        "monday": 40,
        "tuesday": 40,
        "wednesday": 58,
        "thursday": 27,
        "friday": 62,
        "saturday": 42,
        "sunday": 63
      },
      "_today": "wednesday",
      "_today_label": "Repair Culture & Practical Tech",
      "image": "https://100milefreepress.net/wp-content/uploads/sites/15/2026/07/New20Project20-202026-07-22T173901.706.jpg?w=1024"
    },
    {
      "id": "https://www.mycariboonow.com/314986/news/transit/bc-to-triple-public-ev-charging-network-by-2035/",
      "url": "https://www.mycariboonow.com/314986/news/transit/bc-to-triple-public-ev-charging-network-by-2035/",
      "title": "BC to triple public EV charging network by 2035 : My Cariboo Now",
      "content_html": "The B.C. government and BC Hydro said they will add 3,500 public electric-vehicle charging ports by 2035, more than tripling the utility&#x27;s existing public charging network.",
      "date_published": "2026-07-23T06:35:09.739302+00:00",
      "authors": [
        {
          "name": "My Cariboo Now",
          "url": "https://www.mycariboonow.com"
        }
      ],
      "_score": 82,
      "_quality": 77,
      "_relevance": 82,
      "_local_score": 90,
      "_category": "local",
      "_content_type": "news",
      "_selection_bucket": "mid",
      "_theme_scores": {
        "monday": 64,
        "tuesday": 39,
        "wednesday": 3,
        "thursday": 2,
        "friday": 73,
        "saturday": 52,
        "sunday": 76
      },
      "_today": "wednesday",
      "_today_label": "Repair Culture & Practical Tech",
      "image": "https://www.mycariboonow.com/wp-content/uploads/2026/07/PXL_20230515_213857921.PORTRAIT-scaled.jpg"
    },
    {
      "id": "https://thetyee.ca/Analysis/2026/07/23/Logging-Companies-High-Elevation-Forests/",
      "url": "https://thetyee.ca/Analysis/2026/07/23/Logging-Companies-High-Elevation-Forests/",
      "title": "Logging Companies Are Pushing into High-Elevation Forests",
      "content_html": "As BC seeks to increase harvest rates, more trees are falling in areas once considered too remote to log.",
      "date_published": "2026-07-23T07:30:00+00:00",
      "authors": [
        {
          "name": "The Tyee",
          "url": "https://thetyee.ca"
        }
      ],
      "_score": 78,
      "_quality": 81,
      "_relevance": 82,
      "_local_score": 65,
      "_category": "news",
      "_content_type": "analysis",
      "_selection_bucket": "mid",
      "_theme_scores": {
        "monday": 71,
        "tuesday": 61,
        "wednesday": 49,
        "thursday": 65,
        "friday": 66,
        "saturday": 63,
        "sunday": 70
      },
      "_today": "wednesday",
      "_today_label": "Repair Culture & Practical Tech",
      "image": "https://thetyee.ca/News/2026/07/22/LenVanderstarBeforeAfter.jpg"
    },
    {
      "id": "https://www.piquenewsmagazine.com/national-news/with-flames-in-backyard-boston-bar-resident-tells-of-bc-town-surrounded-by-fire-12577538",
      "url": "https://www.piquenewsmagazine.com/national-news/with-flames-in-backyard-boston-bar-resident-tells-of-bc-town-surrounded-by-fire-12577538",
      "title": "With flames in backyard, Boston Bar resident tells of B.C. town surrounded by fire",
      "content_html": "Attila Banhegyi said a tree was burning in the backyard of his home in Boston Bar, B.C., a community now surrounded by fire.",
      "date_published": "2026-07-23T01:11:54+00:00",
      "authors": [
        {
          "name": "Pique Newsmagazine",
          "url": "https://www.piquenewsmagazine.com"
        }
      ],
      "_score": 72,
      "_quality": 68,
      "_relevance": 75,
      "_local_score": 70,
      "_category": "local",
      "_content_type": "feature",
      "_selection_bucket": "mid",
      "_theme_scores": {
        "monday": 72,
        "tuesday": 71,
        "wednesday": 75,
        "thursday": 69,
        "friday": 79,
        "saturday": 72,
        "sunday": 80
      },
      "_today": "wednesday",
      "_today_label": "Repair Culture & Practical Tech",
      "image": "https://www.vmcdn.ca/f/files/shared/feeds/cp/2026/07/6d0ff03ccb9663b2e0f11105d8ce6e850baf284745a7c3d8c7a43f710cd55cc2.jpg;w=960"
    },
    {
      "id": "https://ricochet.media/climate/environment/union-blasts-ford-government-for-mismanagement-of-forest-firefighting-efforts",
      "url": "https://ricochet.media/climate/environment/union-blasts-ford-government-for-mismanagement-of-forest-firefighting-efforts",
      "title": "Union blasts Ford government for ‘mismanagement’ of forest firefighting efforts - Ricochet",
      "content_html": "Despite warnings from the Auditor General, budgets have failed to keep pace with climate change — and northern communities are now paying the price",
      "date_published": "2026-07-23T06:35:46.700608+00:00",
      "authors": [
        {
          "name": "ricochet.media",
          "url": "https://ricochet.media"
        }
      ],
      "_score": 66,
      "_quality": 72,
      "_relevance": 78,
      "_local_score": 25,
      "_category": "news",
      "_content_type": "analysis",
      "_selection_bucket": "mid",
      "_theme_scores": {
        "monday": 61,
        "tuesday": 69,
        "wednesday": 21,
        "thursday": 48,
        "friday": 25,
        "saturday": 66,
        "sunday": 35
      },
      "_today": "wednesday",
      "_today_label": "Repair Culture & Practical Tech",
      "image": "https://www.google.com/s2/favicons?domain=ricochet.media&sz=128"
    },
    {
      "id": "https://quesnelobserver.com/2026/07/22/prince-george-rcmp-search-for-man-wanted-on-multiple-charges-2/",
      "url": "https://quesnelobserver.com/2026/07/22/prince-george-rcmp-search-for-man-wanted-on-multiple-charges-2/",
      "title": "Prince George RCMP search for man wanted on multiple charges",
      "content_html": "## Prince George RCMP search for man wanted on multiple charges Published 11:48 am Wednesday, July 22, 2026 **By Laisa Conde** Vincent John Alexander Rudge is wanted on multiple charges. (Prince George RCMP) Prince George RCMP are asking the public to be on the lookout for 36-year-old Vincent John Alexander Rudge. Rudge has one unendorsed warrant for forcible confinement, assault with a weapon, robbery and aggravated assault. An unendorsed warrant is when a warrant has not been signed by a justice of the peace, meaning the suspect has to be held for a court appearance. Rudge is described as a",
      "date_published": "2026-07-22T18:48:00+00:00",
      "authors": [
        {
          "name": "Quesnel Cariboo Observer",
          "url": "https://quesnelobserver.com"
        }
      ],
      "_score": 62,
      "_quality": 50,
      "_relevance": 62,
      "_local_score": 78,
      "_category": "local",
      "_content_type": "news",
      "_selection_bucket": "mid",
      "_theme_scores": {
        "monday": 20,
        "tuesday": 27,
        "wednesday": 16,
        "thursday": 6,
        "friday": 49,
        "saturday": 28,
        "sunday": 58
      },
      "_today": "wednesday",
      "_today_label": "Repair Culture & Practical Tech",
      "image": "https://quesnelobserver.com/wp-content/uploads/sites/18/2026/07/rudge_fb.jpg?w=1024"
    },
    {
      "id": "https://www.nytimes.com/2026/07/23/business/bangladesh-farmers-diesel-water-iran.html",
      "url": "https://www.nytimes.com/2026/07/23/business/bangladesh-farmers-diesel-water-iran.html",
      "title": "Diesel Crisis Puts Poor Farmers Around the World at Risk",
      "content_html": "The closure of the Strait of Hormuz has limited the shipment of diesel, depriving farmers of fuel for irrigation pumps and threatening the food supply.",
      "date_published": "2026-07-23T04:01:17+00:00",
      "authors": [
        {
          "name": "NYT Business",
          "url": "https://www.nytimes.com/section/business"
        }
      ],
      "_score": 57,
      "_quality": 77,
      "_relevance": 68,
      "_local_score": 0,
      "_category": "news",
      "_content_type": "analysis",
      "_selection_bucket": "mid",
      "_theme_scores": {
        "monday": 68,
        "tuesday": 74,
        "wednesday": 63,
        "thursday": 28,
        "friday": 54,
        "saturday": 67,
        "sunday": 70
      },
      "_today": "wednesday",
      "_today_label": "Repair Culture & Practical Tech",
      "image": "https://static01.nyt.com/images/2026/07/21/multimedia/Biz-Bangladesh-Irrigation-video-still-gmlc/Biz-Bangladesh-Irrigation-video-still-gmlc-mediumSquareAt3X.jpg"
    },
    {
      "id": "https://www.sciencedaily.com/releases/2026/07/260722032108.htm",
      "url": "https://www.sciencedaily.com/releases/2026/07/260722032108.htm",
      "title": "Scientists revive a powerful antibiotic that superbugs had defeated",
      "content_html": "Scientists have found a way to revive vancomycin, a powerful antibiotic that some dangerous bacteria have learned to resist. Instead of creating an entirely new drug, researchers paired vancomycin with a small molecule called pghi-4, which blocks a bacterial enzyme linked to resistance. The combination restored the antibiotic’s ability to kill drug-resistant E. faecium, raising hopes that similar chemical helpers could rescue other failing medicines.",
      "date_published": "2026-07-22T07:21:08+00:00",
      "authors": [
        {
          "name": "ScienceDaily",
          "url": "https://www.sciencedaily.com"
        }
      ],
      "_score": 57,
      "_quality": 78,
      "_relevance": 68,
      "_local_score": 0,
      "_category": "science",
      "_content_type": "feature",
      "_selection_bucket": "mid",
      "_theme_scores": {
        "monday": 68,
        "tuesday": 26,
        "wednesday": 48,
        "thursday": 51,
        "friday": 64,
        "saturday": 75,
        "sunday": 74
      },
      "_today": "wednesday",
      "_today_label": "Repair Culture & Practical Tech",
      "image": "https://www.sciencedaily.com/images/1920/antibiotic-resistance-fighting-bacteria.webp"
    },
    {
      "id": "https://www.producer.com/crops/new-lentil-varieties-highlighted-at-ag-in-motion/",
      "url": "https://www.producer.com/crops/new-lentil-varieties-highlighted-at-ag-in-motion/",
      "title": "New lentil varieties highlighted at Ag in Motion",
      "content_html": "Three new lentil varieties showcased at Ag in Motion, and Ana Vargas shares wins from her breeding program at the Crop Development Centre.",
      "date_published": "2026-07-23T06:35:26.360064+00:00",
      "authors": [
        {
          "name": "Western Producer",
          "url": "https://www.producer.com"
        }
      ],
      "_score": 56,
      "_quality": 62,
      "_relevance": 68,
      "_local_score": 15,
      "_category": "news",
      "_content_type": "feature",
      "_selection_bucket": "mid",
      "_theme_scores": {
        "monday": 14,
        "tuesday": 8,
        "wednesday": 27,
        "thursday": 7,
        "friday": 28,
        "saturday": 15,
        "sunday": 48
      },
      "_today": "wednesday",
      "_today_label": "Repair Culture & Practical Tech",
      "image": "https://www.google.com/s2/favicons?domain=www.producer.com&sz=128"
    },
    {
      "id": "https://www.sciencealert.com/a-significant-public-health-issue-air-pollution-linked-to-higher-parkinsons-risk-in-major-review",
      "url": "https://www.sciencealert.com/a-significant-public-health-issue-air-pollution-linked-to-higher-parkinsons-risk-in-major-review",
      "title": "42 Studies Confirm: Air Pollution Is Linked to Higher Parkinson's Risk",
      "content_html": "<p><img alt=\"42 Studies Confirm: Air Pollution Is Linked to Higher Parkinson&#039;s Risk\" class=\"attachment-large size-large wp-post-image\" height=\"675\" src=\"https://www.sciencealert.com/images/2026/07/Air-pollution-parkinsons.jpg\" style=\"float: left; margin: 0 15px 15px 0;\" width=\"1200\" />\"We urgently need more research.\"</p><p><a href=\"https://www.sciencealert.com/newsletter?utm_source=rss_feed&#038;utm_medium=feed&#038;utm_campaign=rss_feed_promo\" rel=\"noopener\" target=\"_blank\">ScienceAlert stories are written, fact-checked, and edited by humans, never generated by AI. Don&#039;t miss a story, subscribe here.</a></p>",
      "date_published": "2026-07-22T12:00:00+00:00",
      "authors": [
        {
          "name": "ScienceAlert",
          "url": "https://www.sciencealert.com"
        }
      ],
      "_score": 54,
      "_quality": 72,
      "_relevance": 65,
      "_local_score": 0,
      "_category": "wellness",
      "_content_type": "analysis",
      "_selection_bucket": "mid",
      "_theme_scores": {
        "monday": 25,
        "tuesday": 21,
        "wednesday": 29,
        "thursday": 27,
        "friday": 20,
        "saturday": 26,
        "sunday": 18
      },
      "_today": "wednesday",
      "_today_label": "Repair Culture & Practical Tech",
      "image": "https://www.sciencealert.com/images/2026/07/Air-pollution-parkinsons.jpg"
    },
    {
      "id": "https://news.gov.bc.ca/releases/2026PSSG0064-000862",
      "url": "https://news.gov.bc.ca/releases/2026PSSG0064-000862",
      "title": "Minister’s statement on StatCan release of 2025 police-reported crime statistics",
      "content_html": "Nina Krieger, Minister of Public Safety and Solicitor General, has released the following statement in response to Statistics Canada’s release of 2025 police-reported crime statistics:",
      "date_published": "2026-07-22T23:36:00+00:00",
      "authors": [
        {
          "name": "BC Gov News",
          "url": "https://news.gov.bc.ca"
        }
      ],
      "_score": 49,
      "_quality": 40,
      "_relevance": 48,
      "_local_score": 65,
      "_category": "local",
      "_content_type": "wire",
      "_selection_bucket": "border",
      "_theme_scores": {
        "monday": 39,
        "tuesday": 24,
        "wednesday": 38,
        "thursday": 19,
        "friday": 77,
        "saturday": 69,
        "sunday": 75
      },
      "_today": "wednesday",
      "_today_label": "Repair Culture & Practical Tech",
      "image": "https://news.gov.bc.ca/Content/Images/Gov/default-og-image-new.jpg"
    },
    {
      "id": "https://techcrunch.com/2026/07/22/substacks-new-tool-tells-you-whos-been-writing-their-newsletters-with-ai/",
      "url": "https://techcrunch.com/2026/07/22/substacks-new-tool-tells-you-whos-been-writing-their-newsletters-with-ai/",
      "title": "Substack’s new tool tells you who’s been writing their newsletters with AI",
      "content_html": "Substack is giving readers a way to estimate how much of a newsletter was written by AI, signaling a broader shift toward transparency around AI-assisted content.",
      "date_published": "2026-07-22T16:23:09+00:00",
      "authors": [
        {
          "name": "TechCrunch",
          "url": "https://techcrunch.com"
        }
      ],
      "_score": 47,
      "_quality": 68,
      "_relevance": 55,
      "_local_score": 0,
      "_category": "ai-tech",
      "_content_type": "news",
      "_selection_bucket": "border",
      "_theme_scores": {
        "monday": 19,
        "tuesday": 17,
        "wednesday": 12,
        "thursday": 40,
        "friday": 15,
        "saturday": 36,
        "sunday": 18
      },
      "_today": "wednesday",
      "_today_label": "Repair Culture & Practical Tech",
      "image": "https://techcrunch.com/wp-content/uploads/2026/07/substack-GettyImages-2261803485.jpg?w=1024"
    },
    {
      "id": "https://www.aljazeera.com/news/2026/7/23/spain-and-france-battle-raging-wildfires-face-high-risk-of-more?traffic_source=rss",
      "url": "https://www.aljazeera.com/news/2026/7/23/spain-and-france-battle-raging-wildfires-face-high-risk-of-more?traffic_source=rss",
      "title": "Spain and France battle raging wildfires, face high risk of more",
      "content_html": "A wildfire in Spain&#039;s Guadalajara region has burned 32,000 hectares, in one of the country&#039;s largest recorded blazes.",
      "date_published": "2026-07-23T01:23:57+00:00",
      "authors": [
        {
          "name": "Al Jazeera English",
          "url": "https://www.aljazeera.com"
        }
      ],
      "_score": 46,
      "_quality": 65,
      "_relevance": 55,
      "_local_score": 0,
      "_category": "climate",
      "_content_type": "breaking",
      "_selection_bucket": "border",
      "_theme_scores": {
        "monday": 70,
        "tuesday": 41,
        "wednesday": 50,
        "thursday": 25,
        "friday": 67,
        "saturday": 77,
        "sunday": 36
      },
      "_today": "wednesday",
      "_today_label": "Repair Culture & Practical Tech",
      "image": "https://www.aljazeera.com/wp-content/uploads/2026/07/epa_6a60e30b6cb2-1784734475.jpg?resize=1920%2C1440"
    },
    {
      "id": "https://www.techradar.com/pro/white-house-wants-to-shift-billions-of-dollars-of-research-funding-away-from-slow-consensus-peer-review-and-into-individual-scientists-and-ai",
      "url": "https://www.techradar.com/pro/white-house-wants-to-shift-billions-of-dollars-of-research-funding-away-from-slow-consensus-peer-review-and-into-individual-scientists-and-ai",
      "title": "White House wants to shift billions of dollars of research funding away from ‘slow consensus peer review’ and into individual scientists and AI",
      "content_html": "Moving funding to individual scientists and AI could undermine US scientific credibility at home and abroad.",
      "date_published": "2026-07-22T14:34:04+00:00",
      "authors": [
        {
          "name": "TechRadar",
          "url": "https://www.techradar.com"
        }
      ],
      "_score": 46,
      "_quality": 73,
      "_relevance": 50,
      "_local_score": 0,
      "_category": "ai-tech",
      "_content_type": "analysis",
      "_selection_bucket": "border",
      "_theme_scores": {
        "monday": 67,
        "tuesday": 56,
        "wednesday": 74,
        "thursday": 77,
        "friday": 56,
        "saturday": 71,
        "sunday": 77
      },
      "_today": "wednesday",
      "_today_label": "Repair Culture & Practical Tech",
      "image": "https://cdn.mos.cms.futurecdn.net/UtBhmnGFmNskmYUU3kmSaY-1280-80.jpg"
    },
    {
      "id": "https://nautil.us/australias-greater-gliders-fly-majestically-from-tree-to-tree-and-now-we-know-exactly-how-far-1282905/",
      "url": "https://nautil.us/australias-greater-gliders-fly-majestically-from-tree-to-tree-and-now-we-know-exactly-how-far-1282905/",
      "title": "Australia’s Greater Gliders Fly Majestically From Tree to Tree—And Now We Know Exactly How Far",
      "content_html": "<p>It’s not as far as we thought, though</p>\n<p>The post <a href=\"https://nautil.us/australias-greater-gliders-fly-majestically-from-tree-to-tree-and-now-we-know-exactly-how-far-1282905/\">Australia’s Greater Gliders Fly Majestically From Tree to Tree—And Now We Know Exactly How Far</a> appeared first on <a href=\"https://nautil.us\">Nautilus</a>.</p>",
      "date_published": "2026-07-22T19:00:00+00:00",
      "authors": [
        {
          "name": "Nautilus",
          "url": "https://nautil.us/"
        }
      ],
      "_score": 45,
      "_quality": 64,
      "_relevance": 52,
      "_local_score": 0,
      "_category": "science",
      "_content_type": "analysis",
      "_selection_bucket": "mid",
      "_theme_scores": {
        "monday": 22,
        "tuesday": 21,
        "wednesday": 35,
        "thursday": 23,
        "friday": 25,
        "saturday": 7,
        "sunday": 13
      },
      "_today": "wednesday",
      "_today_label": "Repair Culture & Practical Tech",
      "image": "https://lede-admin.nautil.us/wp-content/uploads/sites/70/2026/07/Nield_HERO_4a66b2.png?w=564"
    },
    {
      "id": "https://www.nytimes.com/2026/07/22/us/head-of-miss-halls-school-indicted.html",
      "url": "https://www.nytimes.com/2026/07/22/us/head-of-miss-halls-school-indicted.html",
      "title": "Former Head of All-Girls School Indicted, Accused of Ignoring Abuse Reports",
      "content_html": "Jean Norris, who ran Miss Hall’s School in Massachusetts, was charged with reckless endangerment of a child. A former teacher under her tenure faces three rape charges.",
      "date_published": "2026-07-23T02:24:29+00:00",
      "authors": [
        {
          "name": "NYT Top Stories",
          "url": "https://nytimes.com"
        }
      ],
      "_score": 29,
      "_quality": 75,
      "_relevance": 18,
      "_local_score": 0,
      "_category": "news",
      "_content_type": "breaking",
      "_selection_bucket": "low",
      "_theme_scores": {
        "monday": 61,
        "tuesday": 0,
        "wednesday": 0,
        "thursday": 0,
        "friday": 0,
        "saturday": 0,
        "sunday": 68
      },
      "_today": "wednesday",
      "_today_label": "Repair Culture & Practical Tech",
      "image": "https://static01.nyt.com/images/2026/07/22/us/22nat-hall-s-indictment-upload-from-desktop/22nat-hall-s-indictment-upload-from-desktop-mediumSquareAt3X.jpg"
    },
    {
      "id": "https://www.agweb.com/markets/market-analysis/grains-rally-fresh-highs-adding-risk-premium-cattle-plunge-looking-low",
      "url": "https://www.agweb.com/markets/market-analysis/grains-rally-fresh-highs-adding-risk-premium-cattle-plunge-looking-low",
      "title": "Grains Rally to Fresh Highs Adding Risk Premium: Cattle Plunge Looking for a Low - AgWeb",
      "content_html": "Commodity Market Futures · Futures prices on grains, livestock, oil and more · Farm Journal TV · Trusted ag insights and real stories from rural America. Start your free trial today. Pro Farmer · Join Pro Farmer today to access trusted market intelligence and expert analysis that help you make more confident decisions. Follow Agweb ·",
      "date_published": "2026-07-23T06:35:26.880490+00:00",
      "authors": [
        {
          "name": "AgWeb",
          "url": "https://www.agweb.com"
        }
      ],
      "_score": 29,
      "_quality": 45,
      "_relevance": 32,
      "_local_score": 0,
      "_category": "news",
      "_content_type": "analysis",
      "_selection_bucket": "mid",
      "_theme_scores": {
        "monday": 3,
        "tuesday": 49,
        "wednesday": 5,
        "thursday": 10,
        "friday": 12,
        "saturday": 7,
        "sunday": 6
      },
      "_today": "wednesday",
      "_today_label": "Repair Culture & Practical Tech",
      "image": "https://www.google.com/s2/favicons?domain=www.agweb.com&sz=128"
    },
    {
      "id": "https://www.statnews.com/2026/07/22/maui-wildfire-exposure-study-health-impacts-lahaina-hawaii/?utm_campaign=rss",
      "url": "https://www.statnews.com/2026/07/22/maui-wildfire-exposure-study-health-impacts-lahaina-hawaii/?utm_campaign=rss",
      "title": "As Maui recovers from devastating fires, a study offers vision for new rural health model",
      "content_html": "A study of the long-term health impact of the Lahaina wildfires is inspiring a new model for disaster recovery and support.",
      "date_published": "2026-07-22T08:30:00+00:00",
      "authors": [
        {
          "name": "STAT News",
          "url": "https://www.statnews.com"
        }
      ],
      "_score": 51,
      "_quality": 68,
      "_relevance": 62,
      "_local_score": 0,
      "_category": "wellness",
      "_content_type": "feature",
      "_selection_bucket": "mid",
      "_theme_scores": {
        "monday": 19,
        "tuesday": 25,
        "wednesday": 60,
        "thursday": 42,
        "friday": 33,
        "saturday": 54,
        "sunday": 51
      },
      "_today": "wednesday",
      "_today_label": "Repair Culture & Practical Tech",
      "image": "https://www.statnews.com/wp-content/uploads/2026/07/DSC00073-3-645x645.jpg"
    },
    {
      "id": "https://www.engadget.com/2221309/us-outlines-its-5-billion-genesis-mission-to-boost-science-with-ai/",
      "url": "https://www.engadget.com/2221309/us-outlines-its-5-billion-genesis-mission-to-boost-science-with-ai/",
      "title": "US outlines its $5 billion Genesis Mission to boost science with AI",
      "content_html": "Several federal agencies are contributing toward the interdisciplinary research efforts.",
      "date_published": "2026-07-22T20:54:26+00:00",
      "authors": [
        {
          "name": "Engadget",
          "url": "http://www.engadget.com"
        }
      ],
      "_score": 50,
      "_quality": 63,
      "_relevance": 62,
      "_local_score": 0,
      "_category": "ai-tech",
      "_content_type": "breaking",
      "_selection_bucket": "mid",
      "_theme_scores": {
        "monday": 20,
        "tuesday": 21,
        "wednesday": 17,
        "thursday": 26,
        "friday": 13,
        "saturday": 19,
        "sunday": 28
      },
      "_today": "wednesday",
      "_today_label": "Repair Culture & Practical Tech",
      "image": "https://www.engadget.com/img/gallery/us-outlines-what-its-5-billion-genesis-mission-to-boost-science-with-ai-will-focus-on/l-intro-1784753540.jpg"
    },
    {
      "id": "https://www.businessinsider.com/the-odyssey-christopher-nolan-movie-changes-from-book-odysseus-2026-7",
      "url": "https://www.businessinsider.com/the-odyssey-christopher-nolan-movie-changes-from-book-odysseus-2026-7",
      "title": "Christopher Nolan's 'The Odyssey' changed Odysseus into a hero. It was a mistake.",
      "content_html": "Christopher Nolan's \"The Odyssey\" stars Matt Damon as a noble and heroic Odysseus. It's a change from Homer's original character.",
      "date_published": "2026-07-22T19:53:13+00:00",
      "authors": [
        {
          "name": "Business Insider",
          "url": "https://www.businessinsider.com"
        }
      ],
      "_score": 14,
      "_quality": 40,
      "_relevance": 8,
      "_local_score": 0,
      "_category": "news",
      "_content_type": "opinion",
      "_selection_bucket": "unfiltered",
      "_theme_scores": {
        "monday": 0,
        "tuesday": 0,
        "wednesday": 0,
        "thursday": 0,
        "friday": 0,
        "saturday": 0,
        "sunday": 0
      },
      "_today": "wednesday",
      "_today_label": "Repair Culture & Practical Tech",
      "image": "https://i.insider.com/6a5e4996548c9c486b30e14f?format=jpeg"
    },
    {
      "id": "https://gizmodo.com/drive-faster-than-the-speed-limit-youll-want-to-read-this-2000786993",
      "url": "https://gizmodo.com/drive-faster-than-the-speed-limit-youll-want-to-read-this-2000786993",
      "title": "Drive Faster Than the Speed Limit? You'll Want to Read This",
      "content_html": "While it may feel like speeding shaves a significant amount of time off your commute, the study suggests that driving at or below the speed limit lengthens commute times by just 54 seconds per day, or 6.3 minutes per week, based on the average daily driving distance of 28.6 miles (46.03 kilometers).",
      "date_published": "2026-07-23T06:34:59.396577+00:00",
      "authors": [
        {
          "name": "Gizmodo",
          "url": "https://gizmodo.com/"
        }
      ],
      "_score": 24,
      "_quality": 42,
      "_relevance": 25,
      "_local_score": 0,
      "_category": "news",
      "_content_type": "analysis",
      "_selection_bucket": "unfiltered",
      "_theme_scores": {
        "monday": 14,
        "tuesday": 9,
        "wednesday": 27,
        "thursday": 1,
        "friday": 40,
        "saturday": 37,
        "sunday": 46
      },
      "_today": "wednesday",
      "_today_label": "Repair Culture & Practical Tech"
    },
    {
      "id": "https://kottke.org/26/07/frozen-polygon-waves",
      "url": "https://kottke.org/26/07/frozen-polygon-waves",
      "title": "Frozen Polygon Waves",
      "content_html": "<p></p>\n\t<p></p>\n\t<p>Well, this is just absolutely lovely: photographer and artist <a href=\"https://www.northlandscapes.com\">Jan Erik Waider</a> shot <a href=\"https://www.youtube.com/watch?v=35S6IM_aQ5Q\">these</a> <a href=\"https://www.youtube.com/watch?v=-JQaZaUSS0E\">videos</a> of cracked-but-unbroken Baltic Sea ice undulating with the gentle motion of the sea. Mesmerizing…I could watch these for hours.\n</p>\n \n\n        \n         <p><strong>Tags:</strong> <a href=\"https://kottke.org/tag/Jan%20Erik%20Waider\">Jan Erik Waider</a> · <a href=\"https://kottke.org/tag/mesmerizing\">mesmerizing</a> · <a href=\"https://kottke.org/tag/video\">video</a></p>",
      "date_published": "2026-07-22T20:45:00+00:00",
      "authors": [
        {
          "name": "Kottke.org",
          "url": "https://kottke.org/"
        }
      ],
      "_score": 23,
      "_quality": 38,
      "_relevance": 25,
      "_local_score": 0,
      "_category": "scifi",
      "_content_type": "feature",
      "_selection_bucket": "unfiltered",
      "_theme_scores": {
        "monday": 0,
        "tuesday": 0,
        "wednesday": 0,
        "thursday": 0,
        "friday": 0,
        "saturday": 0,
        "sunday": 0
      },
      "_today": "wednesday",
      "_today_label": "Repair Culture & Practical Tech"
    },
    {
      "id": "https://www.noahpinion.blog/p/who-was-the-worst-monster-of-the",
      "url": "https://www.noahpinion.blog/p/who-was-the-worst-monster-of-the",
      "title": "Who was the worst monster of the 20th century?",
      "content_html": "And who is the worst monster of the 21st?",
      "date_published": "2026-07-22T07:34:05+00:00",
      "authors": [
        {
          "name": "Noahpinion",
          "url": "https://www.noahpinion.blog"
        }
      ],
      "_score": 28,
      "_quality": 48,
      "_relevance": 30,
      "_local_score": 0,
      "_category": "news",
      "_content_type": "opinion",
      "_selection_bucket": "unfiltered",
      "_theme_scores": {
        "monday": 0,
        "tuesday": 0,
        "wednesday": 0,
        "thursday": 0,
        "friday": 0,
        "saturday": 0,
        "sunday": 0
      },
      "_today": "wednesday",
      "_today_label": "Repair Culture & Practical Tech",
      "image": "https://substackcdn.com/image/fetch/$s_!5PGi!,f_auto,q_auto:good,fl_progressive:steep/https%3A%2F%2Fsubstack-post-media.s3.amazonaws.com%2Fpublic%2Fimages%2Ffbbff49e-1a5c-4476-bef3-f0c2da2babfc_768x863.jpeg"
    },
    {
      "id": "https://qz.com/signs-your-pet-is-aging-senior-care-tips",
      "url": "https://qz.com/signs-your-pet-is-aging-senior-care-tips",
      "title": "10 quiet ways your dog or cat shows their age",
      "content_html": "Recognizing these 10 subtle physical, cognitive, and sensory changes in aging dogs and cats allows owners to adapt home environments and medical care for senior pet comfort",
      "date_published": "2026-07-22T20:31:42+00:00",
      "authors": [
        {
          "name": "Quartz",
          "url": "https://qz.com"
        }
      ],
      "_score": 30,
      "_quality": 48,
      "_relevance": 32,
      "_local_score": 0,
      "_category": "wellness",
      "_content_type": "feature",
      "_selection_bucket": "unfiltered",
      "_theme_scores": {
        "monday": 28,
        "tuesday": 19,
        "wednesday": 25,
        "thursday": 18,
        "friday": 39,
        "saturday": 27,
        "sunday": 24
      },
      "_today": "wednesday",
      "_today_label": "Repair Culture & Practical Tech",
      "image": "https://qz.com/cdn-cgi/image/width=600,quality=85,format=auto/https://assets.qz.com/media/pietro-schellino-uz4SEaiVWfM-unsplash.jpg"
    },
    {
      "id": "https://www.themarginalian.org/2026/07/21/hawthorne-life/",
      "url": "https://www.themarginalian.org/2026/07/21/hawthorne-life/",
      "title": "How Not to Waste Your Life",
      "content_html": "&#8220;Let me not seem to have lived in vain,&#8221; the Danish astronomer Tycho Brahe whispered on his deathbed, not realizing that the astronomical tables he was leaving behind would become the portal through which Kepler arrives at the laws of planetary motion; not realizing that the measure of an unwasted life is not what outlives it but how it was lived &#8212; how much integrity and authenticity and creative vitality filled these numbered days, these unrepeatable hours. Most of us will not leave behind a revolutionary insight into the nature of the universe, but we too forget that no matter&#8230;&#160;<a class=\"h3 read_on\" href=\"https://www.themarginalian.org/2026/07/21/hawthorne-life/\">read&#160;article</a>",
      "date_published": "2026-07-21T21:29:44+00:00",
      "authors": [
        {
          "name": "The Marginalian",
          "url": "https://www.themarginalian.org"
        }
      ],
      "_score": 13,
      "_quality": 0,
      "_relevance": 0,
      "_local_score": 0,
      "_category": "science",
      "_content_type": null,
      "_selection_bucket": "unfiltered",
      "_theme_scores": {
        "monday": 28,
        "tuesday": 44,
        "wednesday": 29,
        "thursday": 23,
        "friday": 25,
        "saturday": 22,
        "sunday": 29
      },
      "_today": "wednesday",
      "_today_label": "Repair Culture & Practical Tech"
    },
    {
      "id": "https://www.tomsguide.com/entertainment/prime-video/prime-video-top-10-shows-heres-the-3-worth-binge-watching-this-week-july-22-28",
      "url": "https://www.tomsguide.com/entertainment/prime-video/prime-video-top-10-shows-heres-the-3-worth-binge-watching-this-week-july-22-28",
      "title": "Prime Video top 10 shows — here’s the 3 worth binge-watching this week (July 22-28)",
      "content_html": "Our weekly guide on the three shows currently dominating Prime Video’s top 10 list, including a new action-comedy series sitting in the No. 1 spot.",
      "date_published": "2026-07-22T09:44:39+00:00",
      "authors": [
        {
          "name": "Toms Guide",
          "url": "https://www.tomsguide.com"
        }
      ],
      "_score": 13,
      "_quality": 0,
      "_relevance": 0,
      "_local_score": 0,
      "_category": "news",
      "_content_type": null,
      "_selection_bucket": "unfiltered",
      "_theme_scores": {
        "monday": 0,
        "tuesday": 0,
        "wednesday": 0,
        "thursday": 0,
        "friday": 0,
        "saturday": 0,
        "sunday": 0
      },
      "_today": "wednesday",
      "_today_label": "Repair Culture & Practical Tech",
      "image": "https://cdn.mos.cms.futurecdn.net/RBEkPX8MHun7dvqTrBme8Y-1280-80.jpg"
    },
    {
      "id": "https://www.androidauthority.com/samsung-free-storage-upgrades-europe-3690002/",
      "url": "https://www.androidauthority.com/samsung-free-storage-upgrades-europe-3690002/",
      "title": "Last-minute Galaxy foldable leak has bad news for free storage upgrades",
      "content_html": "An official Samsung email might contain bad news if you were hoping for free storage upgrades.",
      "date_published": "2026-07-22T07:46:49+00:00",
      "authors": [
        {
          "name": "Android Authority",
          "url": "https://www.androidauthority.com"
        }
      ],
      "_score": 19,
      "_quality": 32,
      "_relevance": 20,
      "_local_score": 0,
      "_category": "news",
      "_content_type": "breaking",
      "_selection_bucket": "unfiltered",
      "_theme_scores": {
        "monday": 0,
        "tuesday": 0,
        "wednesday": 0,
        "thursday": 0,
        "friday": 0,
        "saturday": 0,
        "sunday": 0
      },
      "_today": "wednesday",
      "_today_label": "Repair Culture & Practical Tech",
      "image": "https://www.androidauthority.com/wp-content/uploads/2025/07/samsung-galaxy-z-fold-7-open-lying-flat.jpg"
    },
    {
      "id": "https://hackaday.com/2026/07/22/compile-here-run-everywhere-crosstool-ng/",
      "url": "https://hackaday.com/2026/07/22/compile-here-run-everywhere-crosstool-ng/",
      "title": "Compile Here, Run Everywhere: Crosstool-Ng",
      "content_html": "<div><img alt=\"\" class=\"attachment-large size-large wp-post-image\" height=\"484\" src=\"https://hackaday.com/wp-content/uploads/2026/07/CrossCompiling.jpg?w=800\" style=\"margin: 0 auto; margin-bottom: 15px;\" width=\"800\" /></div>In a recent post, I mentioned that I wanted to build some tools for a stripped-down Linux running on a 3D printer with a MIPS CPU. I had two options: <a class=\"read-more\" href=\"https://hackaday.com/2026/07/22/compile-here-run-everywhere-crosstool-ng/\">&#8230;read more</a>",
      "date_published": "2026-07-22T14:00:04+00:00",
      "authors": [
        {
          "name": "Hackaday",
          "url": "https://hackaday.com"
        }
      ],
      "_score": 13,
      "_quality": 0,
      "_relevance": 0,
      "_local_score": 0,
      "_category": "news",
      "_content_type": null,
      "_selection_bucket": "unfiltered",
      "_theme_scores": {
        "monday": 51,
        "tuesday": 29,
        "wednesday": 36,
        "thursday": 28,
        "friday": 15,
        "saturday": 27,
        "sunday": 17
      },
      "_today": "wednesday",
      "_today_label": "Repair Culture & Practical Tech",
      "image": "https://hackaday.com/wp-content/uploads/2026/07/CrossCompiling.jpg"
    },
    {
      "id": "https://kk.org/cooltools/whats-in-my-now-dawn-friedman/",
      "url": "https://kk.org/cooltools/whats-in-my-now-dawn-friedman/",
      "title": "What’s in my NOW? — Dawn Friedman",
      "content_html": "issue #263",
      "date_published": "2026-07-22T16:00:00+00:00",
      "authors": [
        {
          "name": "Cool Tools",
          "url": "https://kk.org/cooltools"
        }
      ],
      "_score": 13,
      "_quality": 0,
      "_relevance": 0,
      "_local_score": 0,
      "_category": "news",
      "_content_type": null,
      "_selection_bucket": "unfiltered",
      "_theme_scores": {
        "monday": 0,
        "tuesday": 0,
        "wednesday": 0,
        "thursday": 0,
        "friday": 0,
        "saturday": 0,
        "sunday": 0
      },
      "_today": "wednesday",
      "_today_label": "Repair Culture & Practical Tech"
    }
  ]
}